INSTALL
LICENSE
MANIFEST.in
README.rst
setup.py
connections/__init__.py
connections/apps.py
connections/models.py
connections/shortcuts.py
connections/signals.py
connections/templatetags/__init__.py
connections/templatetags/connections.py
django_connections.egg-info/PKG-INFO
django_connections.egg-info/SOURCES.txt
django_connections.egg-info/dependency_links.txt
django_connections.egg-info/not-zip-safe
django_connections.egg-info/requires.txt
django_connections.egg-info/top_level.txt
tests/__init__.py
tests/settings.py
tests/test_connections.py
tests/test_relationships.py
tests/test_signals.py
tests/test_templatetags.py